{
  "plays":[{
      "number": 1,
      "position": [1,1],
      "value": "10"
  }, {
      "number": 2,
      "position": [1,1],
      "value": "11"
  }, {
      "number": 3,
      "position": [1,2],
      "value": "11"
  }, {
      "number": 4,
      "position": [1,2],
      "value": "12"
  }, {
      "number": 5,
      "position": [2,2],
      "value": "12"
  }, {
      "number": 6,
      "position": [2,3],
      "value": "13"
  }, {
      "number": 7,
      "position": [2,3],
      "value": "12"
  }, {
      "number": 8,
      "position": [1,4],
      "value": "10"
  }, {
      "number": 9,
      "position": [1,4],
      "value": "11"
  }, {
      "number": 10,
      "position": [1,5],
      "value": "11"
  }, {
      "number": 11,
      "position": [1,5],
      "value": "12"
  }, {
      "number": 12,
      "position": [1,5],
      "value": "13"
  }, {
      "number": 13,
      "position": [2,5],
      "value": "10"
  }, {
      "number": 14,
      "position": [2,5],
      "value": "13"
  }, {
      "number": 15,
      "position": [3,5],
      "value": "12"
  }, {
      "number": 16,
      "position": [3,5],
      "value": "13"
  }, {
      "number": 17,
      "position": [4,5],
      "value": "10"
  }, {
      "number": 18,
      "position": [5,5],
      "value": "11"
  }, {
      "number": 19,
      "position": [5,5],
      "value": "12"
  }, {
      "number": 20,
      "position": [5,5],
      "value": "13"
  }, {
      "number": 21,
      "position": [5,4],
      "value": "13"
  }, {
      "number": 22,
      "position": [5,3],
      "value": "12"
  }, {
      "number": 23,
      "position": [4,3],
      "value": "12"
  }, {
      "number": 24,
      "position": [4,3],
      "value": "11"
  }, {
      "number": 25,
      "position": [4,3],
      "value": "10"
  }, {
      "number": 26,
      "position": [5,2],
      "value": "12"
  }, {
      "number": 27,
      "position": [5,2],
      "value": "13"
  }, {
      "number": 28,
      "position": [5,1],
      "value": "13"
  }, {
      "number": 29,
      "position": [5,1],
      "value": "10"
  }, {
      "number": 30,
      "position": [4,1],
      "value": "13"
  }, {
      "number": 31,
      "position": [4,1],
      "value": "12"
  }, {
      "number": 32,
      "position": [4,1],
      "value": "11"
  }, {
      "number": 33,
      "position": [3,1],
      "value": "10"
  }, {
      "number": 34,
      "position": [3,1],
      "value": "11"
  }, {
      "number": 35,
      "position": [2,1],
      "value": "12"
  }, {
      "number": 36,
      "position": [2,1],
      "value": "11"
  }
  ]
}